method_of_moments/__init__.py
method_of_moments/base.py
method_of_moments/errors.py
method_of_moments/run_pylint.py
method_of_moments/continuous/__init__.py
method_of_moments/continuous/_base_continuous.py
method_of_moments/continuous/_loc_scale.py
method_of_moments/continuous/beta.py
method_of_moments/continuous/generalized_negative_binomial.py
method_of_moments/continuous/normal.py
method_of_moments/discrete/__init__.py
method_of_moments/discrete/_base_discrete.py
method_of_moments/discrete/bernoulli.py
method_of_moments/discrete/binomial.py
method_of_moments/discrete/generalized_poisson.py
method_of_moments/discrete/hypergeometric.py
method_of_moments/discrete/negative_binomial.py
method_of_moments/discrete/poisson.py
method_of_moments/discrete/quasigeometric.py
method_of_moments/discrete/zero_inflated_negative_binomial.py
method_of_moments/tests/__init__.py
method_of_moments/tests/test_continious.py
method_of_moments-0.1.0.dist-info/LICENSE
method_of_moments-0.1.0.dist-info/METADATA
method_of_moments-0.1.0.dist-info/WHEEL
method_of_moments-0.1.0.dist-info/top_level.txt
method_of_moments-0.1.0.dist-info/RECORD
