Metadata-Version: 2.1
Name: method-of-moments
Version: 0.1.0
Summary: The package that allows you to work with probability distributions with a specified mean values and variances.
Home-page: https://github.com/AlbertFarkhutdinov/method_of_moments
Author: Albert Farkhutdinov
Author-email: albertfarhutdinov@gmail.com
License: UNKNOWN
Platform: UNKNOWN
Classifier: Development Status :: 3 - Alpha
Classifier: Programming Language :: Python :: 3.9
Classifier: License :: OSI Approved :: MIT License
Classifier: Operating System :: OS Independent
Requires-Python: >=3.6
License-File: LICENSE
Requires-Dist: math-round-af (==1.0.2)
Requires-Dist: numpy (==1.21.4)
Requires-Dist: pretty-repr (==1.0.1)
Requires-Dist: pylint-af (==1.0.1)
Requires-Dist: pytest (==6.2.5)
Requires-Dist: scipy (==1.7.3)
